Metadata-Version: 1.1
Name: frida-android-adb
Version: 1.2.0
Summary: A pure python implementation of the Android ADB and Fastboot protocols
Home-page: https://github.com/google/python-adb
Author: Fahrzin Hemmati
Author-email: fahhem@google.com
License: UNKNOWN
Keywords: android,adb,fastboot
Platform: UNKNOWN
Classifier: Development Status :: 4 - Beta
Classifier: License :: OSI Approved :: Apache Software License
Classifier: Programming Language :: Python
Classifier: Programming Language :: Python :: 2
Classifier: Programming Language :: Python :: 3
Classifier: Topic :: Software Development :: Testing
